<?xml version="1.0" encoding="UTF-8" standalone="yes"?>
<snapshot version="0.9.9">
<file_presenter>
<text>
<line_numbers>true</line_numbers>
<line_wrap>true</line_wrap>
</text>
</file_presenter>
<screen>
<width>1920</width>
<height>1080</height>
</screen>
<windows>
<selection>0</selection>
<count>1</count>
<window-0>
<window_properties>
<x>57</x>
<width>1485</width>
<y>6</y>
<split_orientation>vertical</split_orientation>
<height>864</height>
</window_properties>
<panels>
<left>
<tree>
<visible>false</visible>
<width>150</width>
</tree>
<tabs>
<selection>0</selection>
<count>1</count>
<tab-0>
<location>file://localhost/C:\bin</location>
<locked>false</locked>
</tab-0>
</tabs>
<file_table>
<date>
<show>true</show>
<width>132</width>
<position>3</position>
</date>
<owner>
<show>false</show>
<width>75</width>
<position>5</position>
</owner>
<extension>
<show>true</show>
<width>24</width>
<position>0</position>
</extension>
<size>
<show>true</show>
<width>60</width>
<position>2</position>
</size>
<permissions>
<show>true</show>
<width>52</width>
<position>4</position>
</permissions>
<name>
<position>1</position>
</name>
<sort>
<by>name</by>
<order>asc</order>
</sort>
<group>
<show>false</show>
<width>75</width>
<position>6</position>
</group>
</file_table>
</left>
<right>
<tree>
<visible>false</visible>
<width>150</width>
</tree>
<tabs>
<selection>1</selection>
<count>2</count>
<tab-0>
<location>file://localhost/C:\Users\Aleksandr.Kuramshin\.m2</location>
<locked>false</locked>
</tab-0>
<tab-1>
<location>file://localhost/C:\Users\Aleksandr.Kuramshin\.trolcommander</location>
<locked>false</locked>
</tab-1>
</tabs>
<file_table>
<date>
<show>true</show>
<width>132</width>
<position>3</position>
</date>
<owner>
<show>false</show>
<width>75</width>
<position>5</position>
</owner>
<extension>
<show>true</show>
<width>24</width>
<position>0</position>
</extension>
<size>
<show>true</show>
<width>60</width>
<position>2</position>
</size>
<permissions>
<show>true</show>
<width>52</width>
<position>4</position>
</permissions>
<name>
<position>1</position>
</name>
<sort>
<by>name</by>
<order>asc</order>
</sort>
<group>
<show>false</show>
<width>75</width>
<position>6</position>
</group>
</file_table>
</right>
</panels>
</window-0>
</windows>
<recent_locations>
<location-79>file://localhost/C:\src\spring-collection\target\classes\com\peterservice</location-79>
<location-77>file://localhost/C:\src\spring-collection.bak</location-77>
<location-78>file://localhost/C:\src\spring-collection\target\classes\com\peterservice\collection</location-78>
<location-71>file://localhost/C:\bin\collection\install\options</location-71>
<location-72>file://localhost/C:\bin\collection\install</location-72>
<location-70>file://localhost/C:\src\bssbox\collection_local_install\target\rms_keys\o_ufm_dms\Source</location-70>
<location-75>file://localhost/C:\src\bssbox</location-75>
<location-76>file://localhost/C:\src\spring-collection\spring-collection</location-76>
<location-73>file://localhost/C:\bin\collection\conf\uadmin</location-73>
<location-74>file://localhost/C:\bin\zkui</location-74>
<location-68>file://localhost/C:\src\bssbox\collection_local_install\target\rms_keys</location-68>
<location-69>file://localhost/C:\src\bssbox\collection_local_install\target\rms_keys\o_ufm_dms</location-69>
<location-66>file://localhost/C:\src\bssbox\collection_local_install\target\collection</location-66>
<location-67>file://localhost/C:\src\bssbox\collection_local_install\target</location-67>
<location-60>file://localhost/C:\src\bssbox\collection_local_install\target\collection\install\mib</location-60>
<location-61>file://localhost/C:\src\bssbox\collection_local_install\target\collection\install\n1ql</location-61>
<location-64>file://localhost/C:\src\bssbox\collection_local_install\target\collection\install</location-64>
<location-65>file://localhost/C:\src\bssbox\collection_local_install\target\collection\lib</location-65>
<location-62>file://localhost/C:\src\bssbox\collection_local_install\target\collection\install\script</location-62>
<location-63>file://localhost/C:\src\bssbox\collection_local_install\target\collection\install\service</location-63>
<location-57>file://localhost/C:\src\bssbox\collection_local_install\target\collection\conf\uadmin</location-57>
<location-58>file://localhost/C:\src\bssbox\collection_local_install\target\collection\conf</location-58>
<location-55>file://localhost/C:\src\bssbox\collection_local_install\target\collection\conf\bis</location-55>
<location-56>file://localhost/C:\src\bssbox\collection_local_install\target\collection\conf\default</location-56>
<location-59>file://localhost/C:\src\bssbox\collection_local_install\target\collection\install\couchbase</location-59>
<location-50>file://localhost/C:\bin\ZooInspector</location-50>
<location-53>file://localhost/C:\src\bssbox\collection_local_install\target\ufm_test_utils</location-53>
<location-54>file://localhost/C:\src\bssbox\collection_local_install\target\collection\bin</location-54>
<location-51>file://localhost/C:\bin\zloader</location-51>
<location-52>file://localhost/C:\src\bssbox\collection_local_install</location-52>
<location-46>file://localhost/C:\src\bssbox\ufm_admin_tools\Source\ufm-admin-tools</location-46>
<location-47>file://localhost/C:\src\bssbox\ufm_admin_tools\Source</location-47>
<location-44>file://localhost/C:\src\bssbox\ufm_admin_tools\Source\ufm-admin-tools\target\ufm-admin-tools-01.00-SNAPSHOT-sources.jar</location-44>
<location-45>file://localhost/C:\src\bssbox\ufm_admin_tools\Source\ufm-admin-tools\target</location-45>
<location-48>file://localhost/C:\src\bssbox\ufm_admin_tools</location-48>
<location-49>file://localhost/C:\downloads\</location-49>
<location-42>file://localhost/C:\src\bssbox\ufm_admin_tools\Source\ufm-admin-tools\target\ufm-admin-tools-01.00-SNAPSHOT-sources.jar\META-INF\</location-42>
<location-43>file://localhost/C:\src\bssbox\ufm_admin_tools\Source\ufm-admin-tools\target\ufm-admin-tools-01.00-SNAPSHOT-sources.jar\bin\</location-43>
<location-40>file://localhost/C:\src\bssbox\ufm_admin_tools\Source\ufm-admin-tools\target\ufm-admin-tools-01.00-SNAPSHOT-sources.jar\install\script\</location-40>
<location-41>file://localhost/C:\src\bssbox\ufm_admin_tools\Source\ufm-admin-tools\target\ufm-admin-tools-01.00-SNAPSHOT-sources.jar\install\</location-41>
<location-35>file://localhost/C:\src\bssbox\ufm_admin_tools\Source\ufm-admin-tools\target\ufm-admin-tools-01.00-SNAPSHOT-sources.jar\com\peterservice\ufm\admintools\preprocessing\</location-35>
<location-36>file://localhost/C:\src\bssbox\ufm_admin_tools\Source\ufm-admin-tools\target\ufm-admin-tools-01.00-SNAPSHOT-sources.jar\com\peterservice\ufm\admintools\</location-36>
<location-33>file://localhost/C:\src\bssbox\ufm_admin_tools\Source\ufm-admin-tools\target\ufm-admin-tools-01.00-SNAPSHOT-sources.jar\com\peterservice\ufm\admintools\exceptions\</location-33>
<location-34>file://localhost/C:\src\bssbox\ufm_admin_tools\Source\ufm-admin-tools\target\ufm-admin-tools-01.00-SNAPSHOT-sources.jar\com\peterservice\ufm\admintools\n1ql\</location-34>
<location-39>file://localhost/C:\src\bssbox\ufm_admin_tools\Source\ufm-admin-tools\target\ufm-admin-tools-01.00-SNAPSHOT-sources.jar\com\</location-39>
<location-37>file://localhost/C:\src\bssbox\ufm_admin_tools\Source\ufm-admin-tools\target\ufm-admin-tools-01.00-SNAPSHOT-sources.jar\com\peterservice\ufm\</location-37>
<location-38>file://localhost/C:\src\bssbox\ufm_admin_tools\Source\ufm-admin-tools\target\ufm-admin-tools-01.00-SNAPSHOT-sources.jar\com\peterservice\</location-38>
<location-31>file://localhost/C:\src\bssbox\ufm_admin_tools\Source\ufm-admin-tools\target\ufm-admin-tools-01.00-SNAPSHOT-sources.jar\com\peterservice\ufm\admintools\clientworker\</location-31>
<location-32>file://localhost/C:\src\bssbox\ufm_admin_tools\Source\ufm-admin-tools\target\ufm-admin-tools-01.00-SNAPSHOT-sources.jar\com\peterservice\ufm\admintools\config\</location-32>
<location-30>file://localhost/C:\src\bssbox\ufm_admin_tools\Source\ufm-admin-tools\target\ufm-admin-tools-01.00-SNAPSHOT-sources.jar\com\peterservice\ufm\admintools\chargedb\</location-30>
<count>100</count>
<location-19>file://localhost/C:\bin\ufm_test_utils</location-19>
<location-24>file://localhost/C:\bin\collection\conf\default</location-24>
<location-25>file://localhost/C:\bin\collection\conf\bis\spring_config</location-25>
<location-22>file://localhost/C:\bin\collection\log</location-22>
<location-23>file://localhost/C:\bin\collection\tzdata</location-23>
<location-28>file://localhost/C:\src\bssbox\ufm_admin_tools\Source\log</location-28>
<location-29>file://localhost/C:\src\bssbox\ufm_admin_tools\Source\ufm-admin-tools\target\ufm-admin-tools-01.00-SNAPSHOT-sources.jar\com\peterservice\ufm\admintools\calatog\</location-29>
<location-26>file://localhost/C:\bin\collection\conf\bis\settings</location-26>
<location-27>file://localhost/C:\src\bssbox\ufm_admin_tools\Source\temp</location-27>
<location-20>file://localhost/C:\bin\collection\lib</location-20>
<location-21>file://localhost/C:\bin\collection\license</location-21>
<location-90>file://localhost/C:\src\spring-collection\target\spring-collection-0.1.0-SNAPSHOT.jar\META-INF\maven\com.peterservice.collection\</location-90>
<location-8>file://localhost/C:\src\bssbox\ufm_cfg\Source\ufm-bundle-bis\install\bin</location-8>
<location-9>file://localhost/C:\src\bssbox\ufm_cfg\Source\ufm-bundle-bis\install\rpm</location-9>
<location-13>file://localhost/C:\src\bssbox\ufm_cfg\Source\ufm-bundle-bis\src\main</location-13>
<location-14>file://localhost/C:\src\bssbox\ufm_cfg\Source\ufm-bundle-bis\src</location-14>
<location-11>file://localhost/C:\src\bssbox\ufm_cfg\Source\ufm-bundle-bis\install</location-11>
<location-99>file://localhost/C:\bin</location-99>
<location-12>file://localhost/C:\src\bssbox\ufm_cfg\Source\ufm-bundle-bis\src\main\resources</location-12>
<location-17>file://localhost/C:\src\bssbox\ufm_cfg</location-17>
<location-18>file://localhost/C:\src\bssbox\ufm_core</location-18>
<location-15>file://localhost/C:\src\bssbox\ufm_cfg\Source\ufm-bundle-bis</location-15>
<location-16>file://localhost/C:\src\bssbox\ufm_cfg\Source</location-16>
<location-93>file://localhost/C:\bin\collection\conf</location-93>
<location-94>file://localhost/C:\bin\collection</location-94>
<location-91>file://localhost/C:\src\spring-collection\target\spring-collection-0.1.0-SNAPSHOT.jar\META-INF\maven\com.peterservice.collection\spring-collection\</location-91>
<location-92>file://localhost/C:\bin\collection\conf\bis</location-92>
<location-97>file://localhost/C:\Users\Aleksandr.Kuramshin\.trolcommander</location-97>
<location-10>file://localhost/C:\src\bssbox\ufm_cfg\Source\ufm-bundle-bis\install\systemd</location-10>
<location-98>file://localhost/C:\</location-98>
<location-95>file://localhost/C:\bin\collection\bin</location-95>
<location-96>file://localhost/C:\Users\Aleksandr.Kuramshin</location-96>
<location-88>file://localhost/C:\src\spring-collection\target\spring-collection-0.1.0-SNAPSHOT.jar\META-INF\</location-88>
<location-89>file://localhost/C:\src\spring-collection\target\spring-collection-0.1.0-SNAPSHOT.jar\META-INF\maven\</location-89>
<location-6>file://localhost/C:\bin\ufm_test_utils\test</location-6>
<location-82>file://localhost/C:\Users\Aleksandr.Kuramshin\.m2</location-82>
<location-7>file://localhost/C:\src\bssbox\ufm_cfg\Source\ufm-bundle-bis\target</location-7>
<location-83>file://localhost/C:\src\</location-83>
<location-4>file://localhost/C:\bin\ufm_test_utils\library\lib</location-4>
<location-80>file://localhost/C:\src\spring-collection\target\classes\com</location-80>
<location-5>file://localhost/C:\bin\ufm_test_utils\library</location-5>
<location-81>file://localhost/C:\src\spring-collection\target\classes</location-81>
<location-2>file://localhost/C:\bin\ufm_test_utils\resource</location-2>
<location-86>file://localhost/C:\src\spring-collection\target\spring-collection-0.1.0-SNAPSHOT.jar\com\</location-86>
<location-3>file://localhost/C:\bin\ufm_test_utils\run</location-3>
<location-87>file://localhost/C:\src\spring-collection\target\spring-collection-0.1.0-SNAPSHOT.jar</location-87>
<location-0>file://localhost/C:\bin\ufm_test_utils\resource\conf</location-0>
<location-84>file://localhost/C:\src\spring-collection</location-84>
<location-1>file://localhost/C:\bin\ufm_test_utils\resource\UFM_GUI</location-1>
<location-85>file://localhost/C:\src\spring-collection\target</location-85>
</recent_locations>
</snapshot>
